MANIFEST.in
README
requirements.txt
setup.py
ajenti.plugin.auth_users.egg-info/PKG-INFO
ajenti.plugin.auth_users.egg-info/SOURCES.txt
ajenti.plugin.auth_users.egg-info/dependency_links.txt
ajenti.plugin.auth_users.egg-info/requires.txt
ajenti.plugin.auth_users.egg-info/top_level.txt
ajenti_plugin_auth_users/README.md
ajenti_plugin_auth_users/__init__.py
ajenti_plugin_auth_users/api.py
ajenti_plugin_auth_users/main.py
ajenti_plugin_auth_users/plugin.yml
ajenti_plugin_auth_users/requirements.txt
ajenti_plugin_auth_users/views.py
ajenti_plugin_auth_users/locale/app.pot
ajenti_plugin_auth_users/locale/af/LC_MESSAGES/app.js
ajenti_plugin_auth_users/locale/af/LC_MESSAGES/app.po
ajenti_plugin_auth_users/locale/af/LC_MESSAGES/app.po~
ajenti_plugin_auth_users/locale/ar/LC_MESSAGES/app.js
ajenti_plugin_auth_users/locale/ar/LC_MESSAGES/app.po
ajenti_plugin_auth_users/locale/ar/LC_MESSAGES/app.po~
ajenti_plugin_auth_users/locale/be/LC_MESSAGES/app.js
ajenti_plugin_auth_users/locale/be/LC_MESSAGES/app.po
ajenti_plugin_auth_users/locale/be/LC_MESSAGES/app.po~
ajenti_plugin_auth_users/locale/bg/LC_MESSAGES/app.js
ajenti_plugin_auth_users/locale/bg/LC_MESSAGES/app.po
ajenti_plugin_auth_users/locale/bg/LC_MESSAGES/app.po~
ajenti_plugin_auth_users/locale/bn/LC_MESSAGES/app.js
ajenti_plugin_auth_users/locale/bn/LC_MESSAGES/app.po
ajenti_plugin_auth_users/locale/bn/LC_MESSAGES/app.po~
ajenti_plugin_auth_users/locale/bs/LC_MESSAGES/app.js
ajenti_plugin_auth_users/locale/bs/LC_MESSAGES/app.po
ajenti_plugin_auth_users/locale/ca/LC_MESSAGES/app.js
ajenti_plugin_auth_users/locale/ca/LC_MESSAGES/app.po
ajenti_plugin_auth_users/locale/ca/LC_MESSAGES/app.po~
ajenti_plugin_auth_users/locale/cs/LC_MESSAGES/app.js
ajenti_plugin_auth_users/locale/cs/LC_MESSAGES/app.po
ajenti_plugin_auth_users/locale/cs/LC_MESSAGES/app.po~
ajenti_plugin_auth_users/locale/da/LC_MESSAGES/app.js
ajenti_plugin_auth_users/locale/da/LC_MESSAGES/app.po
ajenti_plugin_auth_users/locale/da/LC_MESSAGES/app.po~
ajenti_plugin_auth_users/locale/de/LC_MESSAGES/app.js
ajenti_plugin_auth_users/locale/de/LC_MESSAGES/app.po
ajenti_plugin_auth_users/locale/de/LC_MESSAGES/app.po~
ajenti_plugin_auth_users/locale/el/LC_MESSAGES/app.js
