Metadata-Version: 1.2
Name: ajenti.plugin.auth-users
Version: 0.33
Summary: Custom users authentication
Home-page: https://ajenti.org
Author: Ajenti project
Author-email: e@ajenti.org
License: UNKNOWN
Platform: UNKNOWN
Requires-Python: >=3
